kakapo/__init__.py
kakapo/helper_methods.py
kakapo/pyodwrapper.py
test/__init__.py
databricks_kakapo-0.0.2.dist-info/METADATA
databricks_kakapo-0.0.2.dist-info/WHEEL
databricks_kakapo-0.0.2.dist-info/top_level.txt
databricks_kakapo-0.0.2.dist-info/RECORD
