Metadata-Version: 2.1
Name: databricks-kakapo
Version: 0.0.2
Summary: Kakapo: unsupervised outlier detection and integration with mlflow
Home-page: https://github.com/databricks-industry-solutions/rare-event-inspection
Author: Databricks
License: Databricks License
Classifier: License :: Other/Proprietary License
Classifier: Topic :: Scientific/Engineering :: Artificial Intelligence
Classifier: Programming Language :: Python
Classifier: Programming Language :: Python :: 3
Classifier: Programming Language :: Python :: 3.7
Requires-Python: >=3.7.0
Requires-Dist: pyod (>=1.0.7)
Requires-Dist: emmv (>=0.0.4)
Provides-Extra: dev
Requires-Dist: isort ; extra == 'dev'
Requires-Dist: black ; extra == 'dev'
Requires-Dist: build ; extra == 'dev'
